masioware/__init__.py
masioware/tools/__init__.py
masioware/tools/mongo_flask_json_encoder/__init__.py
masioware/tools/onion_requests/__init__.py
masioware/tools/serializer/__init__.py
masioware/tools/sqla_connection_builder/__init__.py
masioware-0.1.0.dist-info/WHEEL
masioware-0.1.0.dist-info/METADATA
masioware-0.1.0.dist-info/RECORD
