Metadata-Version: 2.1
Name: masioware
Version: 0.1.0
Summary: 
Author: Marcio Martinez
Author-email: marcioedumartinez@gmail.com
Requires-Python: >=3.10,<4.0
Classifier: Programming Language :: Python :: 3
Classifier: Programming Language :: Python :: 3.10
Requires-Dist: Flask (>=2.0.2,<3.0.0)
Requires-Dist: bson (>=0.5.10,<0.6.0)
Requires-Dist: isodate (>=0.6.1,<0.7.0)
